pyHelper/pyHelper.py
Ctse-0.1.dist-info/LICENSE
Ctse-0.1.dist-info/METADATA
Ctse-0.1.dist-info/WHEEL
Ctse-0.1.dist-info/top_level.txt
Ctse-0.1.dist-info/RECORD
