Metadata-Version: 2.1
Name: Ctse
Version: 0.1
Summary: For help with progress bar 
Author: Geoloup Team
Author-email: franckiebbb@gmail.com
License-File: LICENSE
